{
  "version": 1,
  "matches": [
    {
      "id": "2026-03-18T01:28:35.429Z",
      "date": "2026-03-18",
      "status": "completed",
      "teams": [
        "Team A",
        "Team B"
      ],
      "maxOvers": 8,
      "innings": [
        {
          "battingTeam": "Team A",
          "bowlingTeam": "Team B",
          "batters": [
            {
              "name": "11",
              "runs": 12,
              "balls": 3,
              "fours": 0,
              "sixes": 2,
              "howOut": null,
              "active": true
            },
            {
              "name": "22",
              "runs": 4,
              "balls": 4,
              "fours": 0,
              "sixes": 0,
              "howOut": "out",
              "active": false
            },
            {
              "name": "55",
              "runs": 0,
              "balls": 0,
              "fours": 0,
              "sixes": 0,
              "howOut": null,
              "active": true
            }
          ],
          "extras": {
            "wides": 0,
            "noBalls": 5,
            "byes": 1,
            "legByes": 1
          },
          "wickets": 1,
          "totalRuns": 23,
          "legalBalls": 7,
          "completed": true,
          "strikerIndex": 2,
          "nonStrikerIndex": 0,
          "needNextBatter": false,
          "currentOverBalls": [
            {
              "d": "W",
              "r": 0
            },
            {
              "d": "Nb",
              "r": 1
            },
            {
              "d": "Nb",
              "r": 1
            },
            {
              "d": "Nb",
              "r": 1
            }
          ],
          "lastOverBalls": [
            {
              "d": "6",
              "r": 6
            },
            {
              "d": "B",
              "r": 1
            },
            {
              "d": "2",
              "r": 2
            },
            {
              "d": "2",
              "r": 2
            },
            {
              "d": "Nb",
              "r": 1
            },
            {
              "d": "Nb",
              "r": 1
            },
            {
              "d": "Lb",
              "r": 1
            },
            {
              "d": "6",
              "r": 6
            }
          ],
          "bowlers": [
            {
              "name": "33",
              "balls": 6,
              "runs": 18,
              "wickets": 0
            },
            {
              "name": "44",
              "balls": 1,
              "runs": 3,
              "wickets": 1
            }
          ],
          "currentBowlerIndex": 1,
          "needNextBowler": false
        },
        {
          "battingTeam": "Team B",
          "bowlingTeam": "Team A",
          "batters": [],
          "extras": {
            "wides": 0,
            "noBalls": 0,
            "byes": 0,
            "legByes": 0
          },
          "wickets": 0,
          "totalRuns": 0,
          "legalBalls": 0,
          "completed": true,
          "strikerIndex": 0,
          "nonStrikerIndex": 1,
          "needNextBatter": false,
          "currentOverBalls": [],
          "lastOverBalls": [],
          "bowlers": [],
          "currentBowlerIndex": -1,
          "needNextBowler": true
        }
      ],
      "currentInningsIndex": 1,
      "result": "Team A won by 23 runs",
      "name": "Match 1 — 17 Mar 2026",
      "matchAuth": {
        "username": "pankaj",
        "passwordHash": "7c78eea7a591b0c8a4dad680372e35ca12e11cffdac5c69a39700c8014fbcc82"
      }
    },
    {
      "id": "2026-03-18T01:30:11.671Z",
      "date": "2026-03-18",
      "status": "completed",
      "teams": [
        "Team A",
        "Team B"
      ],
      "maxOvers": 8,
      "innings": [
        {
          "battingTeam": "Team A",
          "bowlingTeam": "Team B",
          "batters": [
            {
              "name": "11",
              "runs": 7,
              "balls": 3,
              "fours": 0,
              "sixes": 1,
              "howOut": "out",
              "active": false
            },
            {
              "name": "22",
              "runs": 4,
              "balls": 6,
              "fours": 0,
              "sixes": 0,
              "howOut": null,
              "active": true
            },
            {
              "name": "33",
              "runs": 0,
              "balls": 2,
              "fours": 0,
              "sixes": 0,
              "howOut": null,
              "active": true
            }
          ],
          "extras": {
            "wides": 0,
            "noBalls": 2,
            "byes": 6,
            "legByes": 0
          },
          "wickets": 1,
          "totalRuns": 19,
          "legalBalls": 11,
          "completed": true,
          "strikerIndex": 2,
          "nonStrikerIndex": 1,
          "needNextBatter": false,
          "currentOverBalls": [
            {
              "d": "Nb",
              "r": 1
            },
            {
              "d": "2",
              "r": 2
            },
            {
              "d": "2",
              "r": 2
            },
            {
              "d": "B",
              "r": 1
            },
            {
              "d": "B",
              "r": 1
            },
            {
              "d": "B",
              "r": 1
            }
          ],
          "lastOverBalls": [
            {
              "d": "1",
              "r": 1
            },
            {
              "d": "B",
              "r": 1
            },
            {
              "d": "6",
              "r": 6
            },
            {
              "d": "W",
              "r": 0
            },
            {
              "d": "Nb",
              "r": 1
            },
            {
              "d": "B",
              "r": 1
            },
            {
              "d": "B",
              "r": 1
            }
          ],
          "bowlers": [
            {
              "name": "33",
              "balls": 6,
              "runs": 8,
              "wickets": 1
            },
            {
              "name": "1",
              "balls": 5,
              "runs": 5,
              "wickets": 0
            }
          ],
          "currentBowlerIndex": 1,
          "needNextBowler": false
        },
        {
          "battingTeam": "Team B",
          "bowlingTeam": "Team A",
          "batters": [],
          "extras": {
            "wides": 0,
            "noBalls": 0,
            "byes": 0,
            "legByes": 0
          },
          "wickets": 0,
          "totalRuns": 0,
          "legalBalls": 0,
          "completed": true,
          "strikerIndex": 0,
          "nonStrikerIndex": 1,
          "needNextBatter": false,
          "currentOverBalls": [],
          "lastOverBalls": [],
          "bowlers": [],
          "currentBowlerIndex": -1,
          "needNextBowler": true
        }
      ],
      "currentInningsIndex": 1,
      "result": "Team A won by 19 runs",
      "name": "Match 2 — 17 Mar 2026",
      "matchAuth": {
        "username": "pankaj1",
        "passwordHash": "c9b868ed91e7d043f5666feb14f344b8d3dd6d6c44cf605d28b72edab87e8c51"
      }
    },
    {
      "id": "2026-03-18T01:31:22.733Z",
      "date": "2026-03-18",
      "status": "completed",
      "teams": [
        "Team A",
        "Team B"
      ],
      "maxOvers": 8,
      "innings": [
        {
          "battingTeam": "Team A",
          "bowlingTeam": "Team B",
          "batters": [
            {
              "name": "1",
              "runs": 4,
              "balls": 3,
              "fours": 0,
              "sixes": 0,
              "howOut": null,
              "active": true
            },
            {
              "name": "2",
              "runs": 0,
              "balls": 0,
              "fours": 0,
              "sixes": 0,
              "howOut": null,
              "active": true
            }
          ],
          "extras": {
            "wides": 0,
            "noBalls": 0,
            "byes": 1,
            "legByes": 0
          },
          "wickets": 0,
          "totalRuns": 5,
          "legalBalls": 3,
          "completed": true,
          "strikerIndex": 1,
          "nonStrikerIndex": 0,
          "needNextBatter": false,
          "currentOverBalls": [
            {
              "d": "2",
              "r": 2
            },
            {
              "d": "2",
              "r": 2
            },
            {
              "d": "B",
              "r": 1
            }
          ],
          "lastOverBalls": [],
          "bowlers": [
            {
              "name": "11",
              "balls": 3,
              "runs": 4,
              "wickets": 0
            }
          ],
          "currentBowlerIndex": 0,
          "needNextBowler": false
        },
        {
          "battingTeam": "Team B",
          "bowlingTeam": "Team A",
          "batters": [],
          "extras": {
            "wides": 0,
            "noBalls": 0,
            "byes": 0,
            "legByes": 0
          },
          "wickets": 0,
          "totalRuns": 0,
          "legalBalls": 0,
          "completed": true,
          "strikerIndex": 0,
          "nonStrikerIndex": 1,
          "needNextBatter": false,
          "currentOverBalls": [],
          "lastOverBalls": [],
          "bowlers": [],
          "currentBowlerIndex": -1,
          "needNextBowler": true
        }
      ],
      "currentInningsIndex": 1,
      "result": "Team A won by 5 runs",
      "name": "Match 3 — 17 Mar 2026",
      "matchAuth": {
        "username": "pankaj2",
        "passwordHash": "8b645f37a6ee091bdd7a6ceb153396c637f76902d596a8fa1b199694dbf4ca63"
      }
    }
  ],
  "activeDraft": null
}